[{"type":"SkyBox","positionx":-500.0,"positiony":-20000.0,"dimensionx":10000.0,"dimensiony":60000.0,"repeatTexture":false},{"type":"Start","positionx":-100.0,"positiony":0.0,"dimensionx":200.0,"dimensiony":256.0,"textureFilePath":"images/textures/start.png","repeatTexture":false},{"type":"Platform","positionx":-400.0,"positiony":-10100.0,"dimensionx":100.0,"dimensiony":10000.0,"textureFilePath":"images/textures/64TestBlock.png","repeatTexture":true},{"type":"Platform","positionx":300.0,"positiony":-10100.0,"dimensionx":100.0,"dimensiony":10000.0,"textureFilePath":"images/textures/64TestBlock.png","repeatTexture":true},{"type":"Platform","positionx":-300.0,"positiony":-900.0,"dimensionx":400.0,"dimensiony":400.0,"textureFilePath":"images/textures/grass.png","repeatTexture":false},{"type":"Platform","positionx":0.0,"positiony":-2500.0,"dimensionx":300.0,"dimensiony":300.0,"textureFilePath":"images/textures/grass.png","repeatTexture":false},{"type":"Platform","positionx":-300.0,"positiony":-4000.0,"dimensionx":250.0,"dimensiony":250.0,"textureFilePath":"images/textures/grass.png","repeatTexture":false},{"type":"Platform","positionx":50.0,"positiony":-4000.0,"dimensionx":250.0,"dimensiony":250.0,"textureFilePath":"images/textures/grass.png","repeatTexture":false},{"type":"Finish","positionx":-100.0,"positiony":-10000.0,"dimensionx":200.0,"dimensiony":256.0,"textureFilePath":"images/textures/Finish.png","repeatTexture":false},{"type":"Platform","positionx":-100.0,"positiony":-10001.0,"dimensionx":200.0,"dimensiony":1.0,"textureFilePath":"images/textures/platform.png","repeatTexture":true}]
